{"name":"CaretTab","tagline":"CaretTab - New Tab Page Replacement","body":"# CaretTab\r\nCaretTab is a simple New Tab page replacement for Google Chrome.\r\n\r\n## Features\r\n- Displays time on the page and in the tab.\r\n- Toggle display of seconds.\r\n- Search Google from new tab page.\r\n- Toggle display of search box.\r\n- Theme selection. Choose from a handful of different background colors.\r\n\r\nMore features coming soon!\r\n\r\nHave any suggesetions? Let me know on Twitter @BlueCaret\r\n\r\n## Credit\r\nCaretTab was designed and developed by BlueCaret\r\nhttp://bluecaret.com\r\n","google":"UA-63895389-1","note":"Don't delete this file! It's used internally to help with page regeneration."}